<?xml version = '1.0' encoding = 'UTF-8'?>
<Table class="oracle.dbtools.crest.model.design.relational.Table" directorySegmentName="seg_0" id="CFBA9B85-8AFB-745D-714F-109DA202569D" name="TB_ACS_INSTFORM">
<createdBy>logonrmlocal</createdBy>
<createdTime>2023-05-04 01:00:59 UTC</createdTime>
<ownerDesignName>checkpoint3database</ownerDesignName>
<ordsAlias>table_13</ordsAlias>
<allowColumnReorder>false</allowColumnReorder>
<existDependencyGenerateInDDl>true</existDependencyGenerateInDDl>
<parsed>true</parsed>
</Table>